baxa/__init__.py
baxa/version.py
baxa/datasets/__init__.py
baxa/layers/__init__.py
baxa/models/__init__.py
baxa-0.0.2.dist-info/LICENSE
baxa-0.0.2.dist-info/METADATA
baxa-0.0.2.dist-info/WHEEL
baxa-0.0.2.dist-info/top_level.txt
baxa-0.0.2.dist-info/RECORD
